nodestream_github/__init__.py
nodestream_github/audit.py
nodestream_github/client/__init__.py
nodestream_github/client/githubclient.py
nodestream_github/github_audit.yaml
nodestream_github/github_organizations.yaml
nodestream_github/github_repos.yaml
nodestream_github/github_teams.yaml
nodestream_github/github_users.yaml
nodestream_github/interpretations/__init__.py
nodestream_github/interpretations/relationship/__init__.py
nodestream_github/interpretations/relationship/repository.py
nodestream_github/interpretations/relationship/user.py
nodestream_github/logging/__init__.py
nodestream_github/orgs.py
nodestream_github/plugin.py
nodestream_github/repos.py
nodestream_github/teams.py
nodestream_github/transformer/__init__.py
nodestream_github/transformer/repo.py
nodestream_github/types/__init__.py
nodestream_github/types/enums.py
nodestream_github/types/github.py
nodestream_github/types/httpx.py
nodestream_github/users.py
nodestream_plugin_github-0.14.3.dist-info/METADATA
nodestream_plugin_github-0.14.3.dist-info/WHEEL
nodestream_plugin_github-0.14.3.dist-info/entry_points.txt
nodestream_plugin_github-0.14.3.dist-info/RECORD
