Metadata-Version: 2.3
Name: nodestream-plugin-github
Version: 0.14.3
Summary: 
Author: Jon Bristow
Author-email: jonthegm@yahoo.com
Requires-Python: >=3.12,<4.0
Classifier: Programming Language :: Python :: 3
Classifier: Programming Language :: Python :: 3.12
Classifier: Programming Language :: Python :: 3.13
Requires-Dist: freezegun (>=1.5.5,<2.0.0)
Requires-Dist: httpx (>=0.27,<0.28)
Requires-Dist: limits (>=5.5.0,<6.0.0)
Requires-Dist: nodestream (>=0.14.14,<0.15.0)
Requires-Dist: tenacity (>=9.0.0,<10.0.0)
